LICENSE
README.md
pyproject.toml
src/seismic_linter/__init__.py
src/seismic_linter/analyzer.py
src/seismic_linter/caching.py
src/seismic_linter/cli.py
src/seismic_linter/config.py
src/seismic_linter/notebook_handler.py
src/seismic_linter/py.typed
src/seismic_linter/rules.py
src/seismic_linter/runner.py
src/seismic_linter/runtime.py
src/seismic_linter/version.py
src/seismic_linter.egg-info/PKG-INFO
src/seismic_linter.egg-info/SOURCES.txt
src/seismic_linter.egg-info/dependency_links.txt
src/seismic_linter.egg-info/entry_points.txt
src/seismic_linter.egg-info/requires.txt
src/seismic_linter.egg-info/top_level.txt
tests/test_analyzer.py
tests/test_api.py
tests/test_api_notebook.py
tests/test_cli.py
tests/test_cli_config.py
tests/test_components.py
tests/test_fixes.py
tests/test_notebook_list_source.py
tests/test_runtime.py
tests/test_suppression.py