Metadata-Version: 2.4
Name: seismic-linter
Version: 0.2.0
Summary: A static analysis tool for preventing temporal causality leaks in seismology ML.
Author-email: Aman Singh <maintainers@seismic-linter.org>
License: MIT
Project-URL: Homepage, https://github.com/AmanSinghNp/seismic-linter
Project-URL: Repository, https://github.com/AmanSinghNp/seismic-linter
Project-URL: Issues, https://github.com/AmanSinghNp/seismic-linter/issues
Project-URL: Changelog, https://github.com/AmanSinghNp/seismic-linter/blob/main/CHANGELOG.md
Keywords: seismology,machine-learning,static-analysis,linter,temporal-leakage
Classifier: Programming Language :: Python :: 3
Classifier: Programming Language :: Python :: 3.10
Classifier: Programming Language :: Python :: 3.11
Classifier: Programming Language :: Python :: 3.12
Classifier: License :: OSI Approved :: MIT License
Classifier: Operating System :: OS Independent
Classifier: Topic :: Scientific/Engineering :: Physics
Classifier: Topic :: Software Development :: Quality Assurance
Requires-Python: >=3.10
License-File: LICENSE
Requires-Dist: pandas>=1.3.0
Requires-Dist: numpy>=1.20.0
Requires-Dist: ruff>=0.1.15
Requires-Dist: tomli>=2.0.1; python_version < "3.11"
Requires-Dist: nbformat>=5.9.2
Provides-Extra: dev
Requires-Dist: pytest>=8.0.0; extra == "dev"
Requires-Dist: pytest-cov>=4.1.0; extra == "dev"
Requires-Dist: black>=24.1.1; extra == "dev"
Requires-Dist: mypy>=1.8.0; extra == "dev"
Requires-Dist: pre-commit>=3.6.0; extra == "dev"
Dynamic: license-file
